README.md
setup.cfg
setup.py
mersad/__init__.py
mersad/__init__.pyi
mersad/_version.py
mersad/_version.pyi
mersad/py.typed
mersad.egg-info/PKG-INFO
mersad.egg-info/SOURCES.txt
mersad.egg-info/dependency_links.txt
mersad.egg-info/entry_points.txt
mersad.egg-info/requires.txt
mersad.egg-info/top_level.txt
mersad/classical/__init__.py
mersad/classical/__init__.pyi
mersad/classical/affine_cipher.py
mersad/classical/affine_cipher.pyi
mersad/classical/atbash_cipher.py
mersad/classical/atbash_cipher.pyi
mersad/classical/mixalph_cipher.py
mersad/classical/mixalph_cipher.pyi
mersad/classical/shift_cipher.py
mersad/classical/shift_cipher.pyi
mersad/test/__init__.py
mersad/test/__init__.pyi
mersad/test/asset/__init__.py
mersad/test/asset/__init__.pyi
mersad/test/asset/texts/__init__.py
mersad/test/asset/texts/__init__.pyi
mersad/test/classical/__init__.py
mersad/test/classical/__init__.pyi
mersad/test/classical/test_affine_cipher.py
mersad/test/classical/test_affine_cipher.pyi
mersad/test/classical/test_atbash_cipher.py
mersad/test/classical/test_atbash_cipher.pyi
mersad/test/classical/test_mixalph_cipher.py
mersad/test/classical/test_mixalph_cipher.pyi
mersad/test/classical/test_shift_cipher.py
mersad/test/classical/test_shift_cipher.pyi
mersad/test/util/__init__.py
mersad/test/util/__init__.pyi
mersad/test/util/test_base_class.py
mersad/test/util/test_base_class.pyi
mersad/test/util/test_crypto_math.py
mersad/test/util/test_crypto_math.pyi
mersad/test/util/test_string_analyzer.py
mersad/test/util/test_string_analyzer.pyi
mersad/test/util/test_string_manipulation.py
mersad/test/util/test_string_manipulation.pyi
mersad/test/util/test_type_check.py
mersad/test/util/test_type_check.pyi
mersad/util/__init__.py
mersad/util/__init__.pyi
mersad/util/base_class.py
mersad/util/base_class.pyi
mersad/util/crypto_math.py
mersad/util/crypto_math.pyi
mersad/util/string_analyzer.py
mersad/util/string_analyzer.pyi
mersad/util/string_manipulation.py
mersad/util/string_manipulation.pyi
mersad/util/terminal_app_tools.py
mersad/util/terminal_app_tools.pyi
mersad/util/type_check.py
mersad/util/type_check.pyi