Metadata-Version: 2.1
Name: mersad
Version: 0.0.17
Summary: Azadeh Afzar - Mersad Cryptographic Library
Home-page: https://gitlab.com/Azadeh-Afzar/Cryptography/Mersad-Cryptography-Library
Author: Mohammad Mahdi Baghbani Pourvahid
Author-email: MahdiBaghbani@protonmail.com
License: AGPLv3
Platform: Posix; Windows; MacOS X
Classifier: Development Status :: 1 - Planning
Classifier: License :: OSI Approved :: GNU Affero General Public License v3
Classifier: License :: OSI Approved :: zlib/libpng License
Classifier: Operating System :: Unix
Classifier: Operating System :: POSIX :: Linux
Classifier: Operating System :: Microsoft :: Windows
Classifier: Operating System :: MacOS :: MacOS X
Classifier: Environment :: Console
Classifier: Topic :: Security :: Cryptography
Classifier: Topic :: Software Development
Classifier: Topic :: Utilities
Classifier: Intended Audience :: Developers
Classifier: Programming Language :: Python :: 3.6
Classifier: Programming Language :: Python :: 3.7
Requires-Python: >=3.6
